ceshi.py
rdoubao-1.0.0.dist-info/LICENSE.txt
rdoubao-1.0.0.dist-info/METADATA
rdoubao-1.0.0.dist-info/WHEEL
rdoubao-1.0.0.dist-info/top_level.txt
rdoubao-1.0.0.dist-info/RECORD
