Metadata-Version: 2.1
Name: rdoubao
Version: 1.0.0
Summary: doubao
Author-email: rxy <1302553960@qq.com>
Classifier: Programming Language :: Python :: 3
Classifier: License :: OSI Approved :: MIT License
Classifier: Operating System :: OS Independent
Requires-Python: >=3.6
License-File: LICENSE.txt
Requires-Dist: pydantic
Requires-Dist: httpx
